convnets/__init__.py
convnets/datasets/ImageClassificationDataset.py
convnets/datasets/SSLDataset.py
convnets/datasets/__init__.py
convnets/datasets/eurosat.py
convnets/datasets/imagenet.py
convnets/datasets/mnist.py
convnets/datasets/seco.py
convnets/datasets/utils.py
convnets/metrics.py
convnets/models/__init__.py
convnets/models/alexnet.py
convnets/models/barlow.py
convnets/models/lenet/__init__.py
convnets/models/lenet/config.py
convnets/models/lenet/model.py
convnets/models/msfe.py
convnets/models/resnet/__init__.py
convnets/models/resnet/config.py
convnets/models/resnet/model.py
convnets/models/vgg/__init__.py
convnets/models/vgg/config.py
convnets/models/vgg/model.py
convnets/train/__init__.py
convnets/train/barlow.py
convnets/train/fit.py
convnets/train/fit_old.py
convnets/train/utils.py
convnets/utils.py
convnets-0.2.9.dist-info/WHEEL
convnets-0.2.9.dist-info/LICENSE.txt
convnets-0.2.9.dist-info/METADATA
convnets-0.2.9.dist-info/RECORD
