Metadata-Version: 2.1
Name: convnets
Version: 0.2.9
Summary: Convolutional Neural Networks and utilities for Computer Vision
Author: juansensio
Author-email: sensio.juan@gmail.com
Requires-Python: >=3.8,<4.0
Classifier: Programming Language :: Python :: 3
Classifier: Programming Language :: Python :: 3.8
Classifier: Programming Language :: Python :: 3.9
Classifier: Programming Language :: Python :: 3.10
Classifier: Programming Language :: Python :: 3.11
